Workbook

Sheet README
A1: PHI BPMN 2.0 Element Inventory (Rev. B)
A3: Purpose | B3: Every lane, activity, event, gateway and flow in the seven BPMN diagrams, keyed to the element IDs inside the .bpmn files — use it to trace BRD requirements and Odoo configuration back to a diagram element.
A4: Files | B4: One .bpmn file per diagram (see Diagrams sheet). Open in Camunda Modeler, bpmn.io, Signavio, Bizagi or any BPMN 2.0 tool.
A5: ID convention | B5: D<diagram>_<node> for flow nodes, D<diagram>_Flow_n for sequence flows, D<diagram>_MsgFlow_n for message flows, D<diagram>_Lane_<lane> for lanes.
A6: Yellow cells | B6: Input columns: Odoo app / object, BRD requirement ID, notes — fill these during fit-gap sessions.
A7: Example input | B7: Element DC_c9 (task "Generate CTS and payment schedule", diagram C) → Odoo = "Sales order + Sign"; BRD ID = "BR-SAL-014".

Sheet Diagrams
A1: Diagram | B1: Title | C1: Covers processes | D1: BPMN file | E1: Lanes | F1: Tasks | G1: Gateways | H1: Events | I1: Sequence flows | J1: Message flows | K1: Description
A2: A | B2: Plan-to-budget | C2: 01 Budget setup · X1 Forecasts | D2: PHI_A_plan-to-budget.bpmn | E2: =COUNTIFS(Lanes!$A:$A,A2) -> 5 | F2: =COUNTIFS('Flow Nodes'!$A:$A,A2,'Flow Nodes'!$D:$D,"Task") -> 6 | G2: =COUNTIFS('Flow Nodes'!$A:$A,A2,'Flow Nodes'!$D:$D,"*gateway") -> 3 | H2: =COUNTIFS('Flow Nodes'!$A:$A,A2,'Flow Nodes'!$D:$D,"*event") -> 2 | I2: =COUNTIFS('Sequence Flows'!$A:$A,A2) -> 12 | J2: =COUNTIFS('Message Flows'!$A:$A,A2) -> 0 | K2: Annual cycle that produces both the corporate budget and life-of-project budgets, and hands a locked baseline to Accounting so every PR, PO and bill is checked against it.
A3: B | B3: Land-to-inventory | C3: 04 Land acquisition · 05 Project setup · 07 Inventory setup | D3: PHI_B_land-to-inventory.bpmn | E3: =COUNTIFS(Lanes!$A:$A,A3) -> 8 | F3: =COUNTIFS('Flow Nodes'!$A:$A,A3,'Flow Nodes'!$D:$D,"Task") -> 8 | G3: =COUNTIFS('Flow Nodes'!$A:$A,A3,'Flow Nodes'!$D:$D,"*gateway") -> 1 | H3: =COUNTIFS('Flow Nodes'!$A:$A,A3,'Flow Nodes'!$D:$D,"*event") -> 4 | I3: =COUNTIFS('Sequence Flows'!$A:$A,A3) -> 12 | J3: =COUNTIFS('Message Flows'!$A:$A,A3) -> 5 | K3: From a land opportunity to sellable lots: due diligence, agreement, milestone payments, title transfer, project creation, permits and License to Sell, then lot master and price-list creation.
A4: C | B4: Reserve-to-contract | C4: 08 Channel accreditation · 09 Sales · 17 Commissions | D4: PHI_C_reserve-to-contract.bpmn | E4: =COUNTIFS(Lanes!$A:$A,A4) -> 6 | F4: =COUNTIFS('Flow Nodes'!$A:$A,A4,'Flow Nodes'!$D:$D,"Task") -> 9 | G4: =COUNTIFS('Flow Nodes'!$A:$A,A4,'Flow Nodes'!$D:$D,"*gateway") -> 2 | H4: =COUNTIFS('Flow Nodes'!$A:$A,A4,'Flow Nodes'!$D:$D,"*event") -> 3 | I4: =COUNTIFS('Sequence Flows'!$A:$A,A4) -> 15 | J4: =COUNTIFS('Message Flows'!$A:$A,A4) -> 7 | K4: A buyer picks a unit through an in-house or accredited broker; the reservation is receipted, documents and credit are checked, then the CTS and payment schedule are issued and the unit is tagged sold.
A5: D1 | B5: Collect-to-cancel | C5: 11 Accounts monitoring · 12 Cancellations | D5: PHI_D1_collect-to-cancel.bpmn | E5: =COUNTIFS(Lanes!$A:$A,A5) -> 6 | F5: =COUNTIFS('Flow Nodes'!$A:$A,A5,'Flow Nodes'!$D:$D,"Task") -> 7 | G5: =COUNTIFS('Flow Nodes'!$A:$A,A5,'Flow Nodes'!$D:$D,"*gateway") -> 2 | H5: =COUNTIFS('Flow Nodes'!$A:$A,A5,'Flow Nodes'!$D:$D,"*event") -> 5 | I5: =COUNTIFS('Sequence Flows'!$A:$A,A5) -> 14 | J5: =COUNTIFS('Message Flows'!$A:$A,A5) -> 4 | K5: Monthly billing and collection with an event-based gateway: either payment arrives, or the due date plus grace lapses and delinquency handling begins, ending in reinstatement or a Maceda-compliant cancellation that returns the unit to inventory.
A6: D2 | B6: Equity-to-takeout | C6: 13 Bank / Pag-IBIG takeout & IHF | D6: PHI_D2_equity-to-takeout.bpmn | E6: =COUNTIFS(Lanes!$A:$A,A6) -> 6 | F6: =COUNTIFS('Flow Nodes'!$A:$A,A6,'Flow Nodes'!$D:$D,"Task") -> 7 | G6: =COUNTIFS('Flow Nodes'!$A:$A,A6,'Flow Nodes'!$D:$D,"*gateway") -> 2 | H6: =COUNTIFS('Flow Nodes'!$A:$A,A6,'Flow Nodes'!$D:$D,"*event") -> 6 | I6: =COUNTIFS('Sequence Flows'!$A:$A,A6) -> 14 | J6: =COUNTIFS('Message Flows'!$A:$A,A6) -> 5 | K6: Once equity is fully paid the account splits by financing scheme: external loan takeout with lender approval, title annotation and release of proceeds, or in-house financing with an interest-bearing amortization schedule.
A7: E | B7: Procure-to-pay | C7: 03 Corporate expenses · 06 Project expenses · 14 TORC (taxes and other related charges) · 16 AP · 17 Commissions | D7: PHI_E_procure-to-pay.bpmn | E7: =COUNTIFS(Lanes!$A:$A,A7) -> 7 | F7: =COUNTIFS('Flow Nodes'!$A:$A,A7,'Flow Nodes'!$D:$D,"Task") -> 7 | G7: =COUNTIFS('Flow Nodes'!$A:$A,A7,'Flow Nodes'!$D:$D,"*gateway") -> 1 | H7: =COUNTIFS('Flow Nodes'!$A:$A,A7,'Flow Nodes'!$D:$D,"*event") -> 4 | I7: =COUNTIFS('Sequence Flows'!$A:$A,A7) -> 12 | J7: =COUNTIFS('Message Flows'!$A:$A,A7) -> 4 | K7: One pattern for every spend stream in the reference flow — corporate, land, project, sales, TORC, property management and loan payments — so budget checks, approvals, withholding tax and 2307s behave the same everywhere.
A8: F | B8: Turnover-to-title & community | C8: 15 Unit preparation & delivery · 14 TORC · 19 Title delivery · 18 Property management | D8: PHI_F_turnover-to-title-community.bpmn | E8: =COUNTIFS(Lanes!$A:$A,A8) -> 7 | F8: =COUNTIFS('Flow Nodes'!$A:$A,A8,'Flow Nodes'!$D:$D,"Task") -> 10 | G8: =COUNTIFS('Flow Nodes'!$A:$A,A8,'Flow Nodes'!$D:$D,"*gateway") -> 3 | H8: =COUNTIFS('Flow Nodes'!$A:$A,A8,'Flow Nodes'!$D:$D,"*event") -> 5 | I8: =COUNTIFS('Sequence Flows'!$A:$A,A8) -> 18 | J8: =COUNTIFS('Message Flows'!$A:$A,A8) -> 4 | K8: A completed unit is inspected and turned over when the account is eligible; a parallel split then starts homeowner onboarding and the title-transfer track, which ends with the title delivered to the buyer or lender.

Sheet Lanes
A1: Diagram | B1: BPMN ID | C1: Lane / participant | D1: Kind
A2: A | B2: DA_Lane_mc | C2: ManCom / Executive | D2: Lane in PHI pool
A3: A | B3: DA_Lane_fin | C3: Finance – budget & FP&A | D3: Lane in PHI pool
A4: A | B4: DA_Lane_dept | C4: Department heads | D4: Lane in PHI pool
A5: A | B5: DA_Lane_pdd | C5: Project Development | D5: Lane in PHI pool
A6: A | B6: DA_Lane_acc | C6: Accounting | D6: Lane in PHI pool
A7: B | B7: DB_Part_lo | C7: Landowner / seller | D7: External pool (collapsed)
A8: B | B8: DB_Lane_bd | C8: Land acquisition / BD | D8: Lane in PHI pool
A9: B | B9: DB_Lane_mc | C9: ManCom | D9: Lane in PHI pool
A10: B | B10: DB_Lane_legal | C10: Legal & titling | D10: Lane in PHI pool
A11: B | B11: DB_Lane_tre | C11: Treasury & AP | D11: Lane in PHI pool
A12: B | B12: DB_Lane_pdd | C12: Project Development | D12: Lane in PHI pool
... A46: F | B46: DF_Part_gov | C46: BIR, RD, assessor | D46: External pool (collapsed)

Sheet Flow Nodes
A1: Diagram | B1: BPMN ID | C1: Name | D1: Type | E1: Lane | F1: Odoo app / object | G1: BRD requirement ID | H1: Notes
A2: A | B2: DA_a1 | C2: Annual budget cycle opens | D2: Timer start event | E2: Finance – budget & FP&A
A3: A | B3: DA_a2 | C3: Issue budget calendar, templates and analytic structure | D3: Task | E3: Finance – budget & FP&A
A4: A | B4: DA_a3 | D4: Parallel gateway | E4: Finance – budget & FP&A
A5: A | B5: DA_a4 | C5: Prepare corporate and departmental budgets | D5: Task | E5: Department heads
A6: A | B6: DA_a5 | C6: Prepare project budgets by phase and cost code | D6: Task | E6: Project Development
A7: A | B7: DA_a6 | D7: Parallel gateway | E7: Finance – budget & FP&A
A8: A | B8: DA_a7 | C8: Consolidate; test against sales, collection and cash forecasts | D8: Task | E8: Finance – budget & FP&A
A9: A | B9: DA_a8 | C9: Review budget and funding plan | D9: Task | E9: ManCom / Executive
A10: A | B10: DA_a9 | C10: Approved? | D10: Exclusive gateway | E10: ManCom / Executive
A11: A | B11: DA_a10 | C11: Load approved version; switch on budget checks | D11: Task | E11: Accounting
A12: A | B12: DA_a11 | C12: Budget baseline locked | D12: End event | E12: Accounting
A13: B | B13: DB_b1 | C13: Land opportunity logged | D13: Start event | E13: Land acquisition / BD
A14: B | B14: DB_b2 | C14: Due diligence: title, survey, zoning, appraisal | D14: Task | E14: Land acquisition / BD
A15: B | B15: DB_b3 | C15: Evaluate acquisition and feasibility | D15: Task | E15: ManCom
A16: B | B16: DB_b4 | C16: Approve? | D16: Exclusive gateway | E16: ManCom
A17: B | B17: DB_b4n | C17: Declined | D17: End event | E17: ManCom
A18: B | B18: DB_b5 | C18: Negotiate and execute agreement (deed or JV) | D18: Task | E18: Legal & titling
A19: B | B19: DB_b6 | C19: Release milestone payments | D19: Task | E19: Treasury & AP
... A41: D1 | B41: DD1_d2 | C41: Generate and send SOA | D41: Task | E41: Credit & collection
A42: D1 | B42: DD1_d3 | D42: Event-based gateway | E42: Credit & collection
A43: D1 | B43: DD1_d4 | C43: Payment received | D43: Intermediate message catch event | E43: Cashier & accounting
A44: D1 | B44: DD1_d5 | C44: Issue invoice / receipt; allocate to principal, interest, penalties | D44: Task | E44: Cashier & accounting
A45: D1 | B45: DD1_d6 | C45: Account current | D45: End event | E45: Cashier & accounting
A46: D1 | B46: DD1_d7 | C46: Due date + grace lapsed | D46: Intermediate timer catch event | E46: Credit & collection
A47: D1 | B47: DD1_d8 | C47: Compute penalties; send demand letter | D47: Task | E47: Credit & collection
A48: D1 | B48: DD1_d9 | C48: Paid within grace period? | D48: Exclusive gateway | E48: Credit & collection
A49: D1 | B49: DD1_d10 | C49: Compute cash surrender value; serve notarial notice | D49: Task | E49: Legal
A50: D1 | B50: DD1_d11 | C50: Approve cancellation and refund / forfeiture | D50: Task | E50: Approvers (DOA)
A51: D1 | B51: DD1_d12 | C51: Reverse AR and revenue; claw back commission; refund via AP | D51: Task | E51: Cashier & accounting
A52: D1 | B52: DD1_d13 | C52: Return unit to inventory as available | D52: Task | E52: Sales admin / inventory
A53: D1 | B53: DD1_d14 | C53: Unit re-listed | D53: End event | E53: Sales admin / inventory
A54: D2 | B54: DD2_e1 | C54: Equity fully paid | D54: Conditional start event | E54: Credit & collection
... A88: F | B88: DF_g6 | C88: Sign acceptance; hand over keys; start warranty | D88: Task | E88: Customer care / turnover
A89: F | B89: DF_g7 | D89: Parallel gateway | E89: Customer care / turnover
A90: F | B90: DF_g8 | C90: Onboard homeowner; start dues billing | D90: Task | E90: Property management
A91: F | B91: DF_g14 | C91: Service requests, dues collection, PM expenses | D91: Task | E91: Property management
A92: F | B92: DF_g15 | C92: Turn over to HOA when criteria are met | D92: Task | E92: Property management
A93: F | B93: DF_g16 | C93: HOA turned over | D93: End event | E93: Property management
A94: F | B94: DF_g9 | C94: Prepare DOAS; compute and fund TORC (taxes and other related charges) | D94: Task | E94: Titling
A95: F | B95: DF_g10 | C95: Pay taxes and fees; process eCAR and transfer | D95: Task | E95: Titling
A96: F | B96: DF_g11 | C96: New TCT / CCT issued | D96: Intermediate message catch event | E96: Titling
A97: F | B97: DF_g12 | C97: Deliver title to buyer or lender | D97: Task | E97: Titling
A98: F | B98: DF_g13 | C98: Title delivered | D98: End event | E98: Titling

Sheet Sequence Flows
A1: Diagram | B1: BPMN ID | C1: Source ID | D1: Source | E1: Target ID | F1: Target | G1: Condition / label
A2: A | B2: DA_Flow_1 | C2: DA_a1 | D2: Annual budget cycle opens | E2: DA_a2 | F2: Issue budget calendar, templates and analytic structure
A3: A | B3: DA_Flow_2 | C3: DA_a2 | D3: Issue budget calendar, templates and analytic structure | E3: DA_a3 | F3: Parallel gateway
A4: A | B4: DA_Flow_3 | C4: DA_a3 | D4: Parallel gateway | E4: DA_a4 | F4: Prepare corporate and departmental budgets
A5: A | B5: DA_Flow_4 | C5: DA_a3 | D5: Parallel gateway | E5: DA_a5 | F5: Prepare project budgets by phase and cost code
A6: A | B6: DA_Flow_5 | C6: DA_a4 | D6: Prepare corporate and departmental budgets | E6: DA_a6 | F6: Parallel gateway
A7: A | B7: DA_Flow_6 | C7: DA_a5 | D7: Prepare project budgets by phase and cost code | E7: DA_a6 | F7: Parallel gateway
A8: A | B8: DA_Flow_7 | C8: DA_a6 | D8: Parallel gateway | E8: DA_a7 | F8: Consolidate; test against sales, collection and cash forecasts
A9: A | B9: DA_Flow_8 | C9: DA_a7 | D9: Consolidate; test against sales, collection and cash forecasts | E9: DA_a8 | F9: Review budget and funding plan
A10: A | B10: DA_Flow_9 | C10: DA_a8 | D10: Review budget and funding plan | E10: DA_a9 | F10: Approved?
A11: A | B11: DA_Flow_10 | C11: DA_a9 | D11: Approved? | E11: DA_a10 | F11: Load approved version; switch on budget checks | G11: Yes
A12: A | B12: DA_Flow_11 | C12: DA_a9 | D12: Approved? | E12: DA_a7 | F12: Consolidate; test against sales, collection and cash forecasts | G12: No – revise
A13: A | B13: DA_Flow_12 | C13: DA_a10 | D13: Load approved version; switch on budget checks | E13: DA_a11 | F13: Budget baseline locked
A14: B | B14: DB_Flow_1 | C14: DB_b1 | D14: Land opportunity logged | E14: DB_b2 | F14: Due diligence: title, survey, zoning, appraisal
A15: B | B15: DB_Flow_2 | C15: DB_b2 | D15: Due diligence: title, survey, zoning, appraisal | E15: DB_b3 | F15: Evaluate acquisition and feasibility
A16: B | B16: DB_Flow_3 | C16: DB_b3 | D16: Evaluate acquisition and feasibility | E16: DB_b4 | F16: Approve?
A17: B | B17: DB_Flow_4 | C17: DB_b4 | D17: Approve? | E17: DB_b4n | F17: Declined | G17: No
A18: B | B18: DB_Flow_5 | C18: DB_b4 | D18: Approve? | E18: DB_b5 | F18: Negotiate and execute agreement (deed or JV) | G18: Yes
A19: B | B19: DB_Flow_6 | C19: DB_b5 | D19: Negotiate and execute agreement (deed or JV) | E19: DB_b6 | F19: Release milestone payments
A20: B | B20: DB_Flow_7 | C20: DB_b6 | D20: Release milestone payments | E20: DB_b7 | F20: Pay CGT, DST and transfer tax; file for transfer
A21: B | B21: DB_Flow_8 | C21: DB_b7 | D21: Pay CGT, DST and transfer tax; file for transfer | E21: DB_b8 | F21: New title issued
A22: B | B22: DB_Flow_9 | C22: DB_b8 | D22: New title issued | E22: DB_b9 | F22: Create project, phases, WBS and analytic account
A23: B | B23: DB_Flow_10 | C23: DB_b9 | D23: Create project, phases, WBS and analytic account | E23: DB_b10 | F23: Secure permits and License to Sell
A24: B | B24: DB_Flow_11 | C24: DB_b10 | D24: Secure permits and License to Sell | E24: DB_b11 | F24: Create lots (unit master), price list and financing options
A25: B | B25: DB_Flow_12 | C25: DB_b11 | D25: Create lots (unit master), price list and financing options | E25: DB_b12 | F25: Units open for sale
A26: C | B26: DC_Flow_1 | C26: DC_c1 | D26: Buyer selects unit and scheme | E26: DC_c2 | F26: Prepare sales computation (TCP, discounts, charges, terms)
A27: C | B27: DC_Flow_2 | C27: DC_c2 | D27: Prepare sales computation (TCP, discounts, charges, terms) | E27: DC_c3 | F27: Discount within authority?
A28: C | B28: DC_Flow_3 | C28: DC_c3 | D28: Discount within authority? | E28: DC_c4 | F28: Reservation fee received | G28: Yes
A29: C | B29: DC_Flow_4 | C29: DC_c3 | D29: Discount within authority? | E29: DC_c3n | F29: Approve special discount | G29: No
A30: C | B30: DC_Flow_5 | C30: DC_c3n | D30: Approve special discount | E30: DC_c4 | F30: Reservation fee received
A31: C | B31: DC_Flow_6 | C31: DC_c4 | D31: Reservation fee received | E31: DC_c5 | F31: Issue invoice / receipt; post reservation fee
A32: C | B32: DC_Flow_7 | C32: DC_c5 | D32: Issue invoice / receipt; post reservation fee | E32: DC_c6 | F32: Tag unit reserved; create buyer and co-borrower records
A33: C | B33: DC_Flow_8 | C33: DC_c6 | D33: Tag unit reserved; create buyer and co-borrower records | E33: DC_c7 | F33: Check documents and credit per financing scheme
A34: C | B34: DC_Flow_9 | C34: DC_c7 | D34: Check documents and credit per financing scheme | E34: DC_c8 | F34: Complete and qualified?
A35: C | B35: DC_Flow_10 | C35: DC_c8 | D35: Complete and qualified? | E35: DC_c9 | F35: Generate CTS and payment schedule | G35: Yes
A36: C | B36: DC_Flow_11 | C36: DC_c8 | D36: Complete and qualified? | E36: DC_c8n | F36: Follow up deficiencies before reservation expires | G36: No
A37: C | B37: DC_Flow_12 | C37: DC_c8n | D37: Follow up deficiencies before reservation expires | E37: DC_c7 | F37: Check documents and credit per financing scheme
A38: C | B38: DC_Flow_13 | C38: DC_c9 | D38: Generate CTS and payment schedule | E38: DC_c10 | F38: Countersign and notarize CTS
A39: C | B39: DC_Flow_14 | C39: DC_c10 | D39: Countersign and notarize CTS | E39: DC_c11 | F39: Tag unit sold; accrue broker commission
A40: C | B40: DC_Flow_15 | C40: DC_c11 | D40: Tag unit sold; accrue broker commission | E40: DC_c12 | F40: Account handed to accounts monitoring
A41: D1 | B41: DD1_Flow_1 | C41: DD1_d1 | D41: Installment due per schedule | E41: DD1_d2 | F41: Generate and send SOA
A42: D1 | B42: DD1_Flow_2 | C42: DD1_d2 | D42: Generate and send SOA | E42: DD1_d3 | F42: Event-based gateway
A43: D1 | B43: DD1_Flow_3 | C43: DD1_d3 | D43: Event-based gateway | E43: DD1_d4 | F43: Payment received
A44: D1 | B44: DD1_Flow_4 | C44: DD1_d3 | D44: Event-based gateway | E44: DD1_d7 | F44: Due date + grace lapsed
A45: D1 | B45: DD1_Flow_5 | C45: DD1_d4 | D45: Payment received | E45: DD1_d5 | F45: Issue invoice / receipt; allocate to principal, interest, penalties
A46: D1 | B46: DD1_Flow_6 | C46: DD1_d5 | D46: Issue invoice / receipt; allocate to principal, interest, penalties | E46: DD1_d6 | F46: Account current
A47: D1 | B47: DD1_Flow_7 | C47: DD1_d7 | D47: Due date + grace lapsed | E47: DD1_d8 | F47: Compute penalties; send demand letter
A48: D1 | B48: DD1_Flow_8 | C48: DD1_d8 | D48: Compute penalties; send demand letter | E48: DD1_d9 | F48: Paid within grace period?
A49: D1 | B49: DD1_Flow_9 | C49: DD1_d9 | D49: Paid within grace period? | E49: DD1_d5 | F49: Issue invoice / receipt; allocate to principal, interest, penalties | G49: Yes
A50: D1 | B50: DD1_Flow_10 | C50: DD1_d9 | D50: Paid within grace period? | E50: DD1_d10 | F50: Compute cash surrender value; serve notarial notice | G50: No
A51: D1 | B51: DD1_Flow_11 | C51: DD1_d10 | D51: Compute cash surrender value; serve notarial notice | E51: DD1_d11 | F51: Approve cancellation and refund / forfeiture
A52: D1 | B52: DD1_Flow_12 | C52: DD1_d11 | D52: Approve cancellation and refund / forfeiture | E52: DD1_d12 | F52: Reverse AR and revenue; claw back commission; refund via AP
A53: D1 | B53: DD1_Flow_13 | C53: DD1_d12 | D53: Reverse AR and revenue; claw back commission; refund via AP | E53: DD1_d13 | F53: Return unit to inventory as available
A54: D1 | B54: DD1_Flow_14 | C54: DD1_d13 | D54: Return unit to inventory as available | E54: DD1_d14 | F54: Unit re-listed
A55: D2 | B55: DD2_Flow_1 | C55: DD2_e1 | D55: Equity fully paid | E55: DD2_e2 | F55: Financing scheme?
A56: D2 | B56: DD2_Flow_2 | C56: DD2_e2 | D56: Financing scheme? | E56: DD2_e3 | F56: Collect and check loan requirements | G56: Bank / Pag-IBIG
A57: D2 | B57: DD2_Flow_3 | C57: DD2_e2 | D57: Financing scheme? | E57: DD2_e11 | F57: Evaluate and approve IHF | G57: IHF
A58: D2 | B58: DD2_Flow_4 | C58: DD2_e3 | D58: Collect and check loan requirements | E58: DD2_e4 | F58: Submit loan application
A59: D2 | B59: DD2_Flow_5 | C59: DD2_e4 | D59: Submit loan application | E59: DD2_e5 | F59: Lender decision received
A60: D2 | B60: DD2_Flow_6 | C60: DD2_e5 | D60: Lender decision received | E60: DD2_e6 | F60: Approved in full?
A61: D2 | B61: DD2_Flow_7 | C61: DD2_e6 | D61: Approved in full? | E61: DD2_e7 | F61: Execute DOAS; annotate mortgage on title | G61: Yes
A62: D2 | B62: DD2_Flow_8 | C62: DD2_e6 | D62: Approved in full? | E62: DD2_e6n | F62: Buyer covers shortfall or re-routes to IHF, cash or cancellation | G62: No
A63: D2 | B63: DD2_Flow_9 | C63: DD2_e6n | D63: Buyer covers shortfall or re-routes to IHF, cash or cancellation | E63: DD2_e6e | F63: Re-routed per policy
A64: D2 | B64: DD2_Flow_10 | C64: DD2_e7 | D64: Execute DOAS; annotate mortgage on title | E64: DD2_e8 | F64: Loan proceeds received
A65: D2 | B65: DD2_Flow_11 | C65: DD2_e8 | D65: Loan proceeds received | E65: DD2_e9 | F65: Apply proceeds; close buyer balance
A66: D2 | B66: DD2_Flow_12 | C66: DD2_e9 | D66: Apply proceeds; close buyer balance | E66: DD2_e10 | F66: Fully paid – ready for title
A67: D2 | B67: DD2_Flow_13 | C67: DD2_e11 | D67: Evaluate and approve IHF | E67: DD2_e12 | F67: Set up IHF amortization with interest
A68: D2 | B68: DD2_Flow_14 | C68: DD2_e12 | D68: Set up IHF amortization with interest | E68: DD2_e13 | F68: Handed to monthly collection
A69: E | B69: DE_Flow_1 | C69: DE_f1 | D69: Spend need arises | E69: DE_f2 | F69: Raise purchase or payment request with budget line
A70: E | B70: DE_Flow_2 | C70: DE_f2 | D70: Raise purchase or payment request with budget line | E70: DE_f3 | F70: Budget available?
A71: E | B71: DE_Flow_3 | C71: DE_f3 | D71: Budget available? | E71: DE_f4 | F71: Source and issue PO or contract | G71: Yes
A72: E | B72: DE_Flow_4 | C72: DE_f3 | D72: Budget available? | E72: DE_f3n | F72: Realign budget or get exception approval | G72: No
A73: E | B73: DE_Flow_5 | C73: DE_f3n | D73: Realign budget or get exception approval | E73: DE_f4 | F73: Source and issue PO or contract
A74: E | B74: DE_Flow_6 | C74: DE_f4 | D74: Source and issue PO or contract | E74: DE_f5 | F74: Delivered or accomplished
A75: E | B75: DE_Flow_7 | C75: DE_f5 | D75: Delivered or accomplished | E75: DE_f6 | F75: Verify receipt or % accomplishment; update progress
A76: E | B76: DE_Flow_8 | C76: DE_f6 | D76: Verify receipt or % accomplishment; update progress | E76: DE_f7 | F76: Vendor bill received
A77: E | B77: DE_Flow_9 | C77: DE_f7 | D77: Vendor bill received | E77: DE_f8 | F77: 3-way match; compute VAT, EWT, retention
A78: E | B78: DE_Flow_10 | C78: DE_f8 | D78: 3-way match; compute VAT, EWT, retention | E78: DE_f9 | F78: Approve per DOA matrix
A79: E | B79: DE_Flow_11 | C79: DE_f9 | D79: Approve per DOA matrix | E79: DE_f10 | F79: Release payment; issue BIR 2307
A80: E | B80: DE_Flow_12 | C80: DE_f10 | D80: Release payment; issue BIR 2307 | E80: DE_f11 | F80: Paid; actuals vs budget updated
A81: F | B81: DF_Flow_1 | C81: DF_g1 | D81: Unit ready for occupancy | E81: DF_g2 | F81: Internal QA and punch list
A82: F | B82: DF_Flow_2 | C82: DF_g2 | D82: Internal QA and punch list | E82: DF_g3 | F82: Turnover-eligible?
A83: F | B83: DF_Flow_3 | C83: DF_g3 | D83: Turnover-eligible? | E83: DF_g4 | F83: Schedule turnover and joint inspection | G83: Yes
A84: F | B84: DF_Flow_4 | C84: DF_g3 | D84: Turnover-eligible? | E84: DF_g3n | F84: Hold until eligible | G84: No
A85: F | B85: DF_Flow_5 | C85: DF_g4 | D85: Schedule turnover and joint inspection | E85: DF_g5 | F85: Buyer accepts unit?
A86: F | B86: DF_Flow_6 | C86: DF_g5 | D86: Buyer accepts unit? | E86: DF_g6 | F86: Sign acceptance; hand over keys; start warranty | G86: Yes
A87: F | B87: DF_Flow_7 | C87: DF_g5 | D87: Buyer accepts unit? | E87: DF_g5n | F87: Rectify defects | G87: No
A88: F | B88: DF_Flow_8 | C88: DF_g5n | D88: Rectify defects | E88: DF_g4 | F88: Schedule turnover and joint inspection
A89: F | B89: DF_Flow_9 | C89: DF_g6 | D89: Sign acceptance; hand over keys; start warranty | E89: DF_g7 | F89: Parallel gateway
A90: F | B90: DF_Flow_10 | C90: DF_g7 | D90: Parallel gateway | E90: DF_g8 | F90: Onboard homeowner; start dues billing
A91: F | B91: DF_Flow_11 | C91: DF_g7 | D91: Parallel gateway | E91: DF_g9 | F91: Prepare DOAS; compute and fund TORC (taxes and other related charges)
A92: F | B92: DF_Flow_12 | C92: DF_g8 | D92: Onboard homeowner; start dues billing | E92: DF_g14 | F92: Service requests, dues collection, PM expenses
A93: F | B93: DF_Flow_13 | C93: DF_g14 | D93: Service requests, dues collection, PM expenses | E93: DF_g15 | F93: Turn over to HOA when criteria are met
A94: F | B94: DF_Flow_14 | C94: DF_g15 | D94: Turn over to HOA when criteria are met | E94: DF_g16 | F94: HOA turned over
A95: F | B95: DF_Flow_15 | C95: DF_g9 | D95: Prepare DOAS; compute and fund TORC (taxes and other related charges) | E95: DF_g10 | F95: Pay taxes and fees; process eCAR and transfer
A96: F | B96: DF_Flow_16 | C96: DF_g10 | D96: Pay taxes and fees; process eCAR and transfer | E96: DF_g11 | F96: New TCT / CCT issued
A97: F | B97: DF_Flow_17 | C97: DF_g11 | D97: New TCT / CCT issued | E97: DF_g12 | F97: Deliver title to buyer or lender
A98: F | B98: DF_Flow_18 | C98: DF_g12 | D98: Deliver title to buyer or lender | E98: DF_g13 | F98: Title delivered

Sheet Message Flows
A1: Diagram | B1: BPMN ID | C1: Message | D1: Source ID | E1: Source | F1: Target ID | G1: Target
A2: B | B2: DB_MsgFlow_1 | C2: Signed agreement | D2: DB_b5 | E2: Negotiate and execute agreement (deed or JV) | F2: DB_Part_lo | G2: Landowner / seller (pool)
A3: B | B3: DB_MsgFlow_2 | C3: Milestone payment | D3: DB_b6 | E3: Release milestone payments | F3: DB_Part_lo | G3: Landowner / seller (pool)
A4: B | B4: DB_MsgFlow_3 | C4: Taxes and transfer documents | D4: DB_b7 | E4: Pay CGT, DST and transfer tax; file for transfer | F4: DB_Part_gov | G4: BIR, RD, LGU, DHSUD (pool)
A5: B | B5: DB_MsgFlow_4 | C5: eCAR, new TCT | D5: DB_Part_gov | E5: BIR, RD, LGU, DHSUD (pool) | F5: DB_b8 | G5: New title issued
A6: B | B6: DB_MsgFlow_5 | C6: Permit and LTS applications | D6: DB_b10 | E6: Secure permits and License to Sell | F6: DB_Part_gov | G6: BIR, RD, LGU, DHSUD (pool)
A7: C | B7: DC_MsgFlow_1 | C7: Reservation request | D7: DC_Part_buyer | E7: Buyer (pool) | F7: DC_c1 | G7: Buyer selects unit and scheme
A8: C | B8: DC_MsgFlow_2 | C8: Sales computation | D8: DC_c2 | E8: Prepare sales computation (TCP, discounts, charges, terms) | F8: DC_Part_buyer | G8: Buyer (pool)
A9: C | B9: DC_MsgFlow_3 | C9: Reservation fee | D9: DC_Part_buyer | E9: Buyer (pool) | F9: DC_c4 | G9: Reservation fee received
A10: C | B10: DC_MsgFlow_4 | C10: Invoice / receipt | D10: DC_c5 | E10: Issue invoice / receipt; post reservation fee | F10: DC_Part_buyer | G10: Buyer (pool)
A11: C | B11: DC_MsgFlow_5 | C11: KYC and financing documents | D11: DC_Part_buyer | E11: Buyer (pool) | F11: DC_c7 | G11: Check documents and credit per financing scheme
A12: C | B12: DC_MsgFlow_6 | C12: CTS for signature | D12: DC_c9 | E12: Generate CTS and payment schedule | F12: DC_Part_buyer | G12: Buyer (pool)
... A30: F | B30: DF_MsgFlow_4 | C30: Title (or to lender) | D30: DF_g12 | E30: Deliver title to buyer or lender | F30: DF_Part_buyer | G30: Buyer (pool)
